proxy_machine/__init__.py
proxy_machine/__main__.py
proxy_machine/otherproxies.py
proxy_machine/proxyarchive.py
proxy_machine/proxyscrape_all.py
proxy_machine/tools/proxies_manipulation.py
proxy_machine/tools/proxy_checker.py
proxy_machine-0.1.0.dist-info/entry_points.txt
proxy_machine-0.1.0.dist-info/LICENSE
proxy_machine-0.1.0.dist-info/WHEEL
proxy_machine-0.1.0.dist-info/METADATA
proxy_machine-0.1.0.dist-info/RECORD
