Metadata-Version: 2.1
Name: proxy-machine
Version: 0.1.0
Summary: Parse 30.000 free proxies!
Home-page: https://github.com/zekiblue/proxy_machine
License: GPL-3.0-only
Author: batiscuff
Author-email: batiscuff@gmail.com
Requires-Python: >=3.9,<4.0
Classifier: License :: OSI Approved :: GNU General Public License v3 (GPLv3)
Classifier: Programming Language :: Python :: 3
Classifier: Programming Language :: Python :: 3.10
Classifier: Programming Language :: Python :: 3.9
Requires-Dist: Brotli (>=1.0.9,<2.0.0)
Requires-Dist: beautifulsoup4 (==4.9.3)
Requires-Dist: httpx (>=0.19.0,<0.20.0)
Requires-Dist: lxml (==4.6.2)
Requires-Dist: proxyscrape (==0.3.0)
Requires-Dist: requests (>=2.25.1,<3.0.0)
Requires-Dist: typer (>=0.4.0,<0.5.0)
Requires-Dist: user_agent (==0.1.9)
Project-URL: Repository, https://github.com/zekiblue/proxy_machine
